wsmprpc/__init__.py
wsmprpc/client.py
wsmprpc/error.py
wsmprpc/msg_type.py
wsmprpc/rpc_stream.py
wsmprpc/server.py
wsmprpc-1.1.3.dist-info/DESCRIPTION.rst
wsmprpc-1.1.3.dist-info/METADATA
wsmprpc-1.1.3.dist-info/RECORD
wsmprpc-1.1.3.dist-info/WHEEL
wsmprpc-1.1.3.dist-info/metadata.json
wsmprpc-1.1.3.dist-info/top_level.txt
