Metadata-Version: 2.0
Name: wsmprpc
Version: 1.1.3
Summary: python msgpack RPC over websocket
Home-page: https://github.com/hyansuper/wsmprpc
Author: Huang Yan
Author-email: hyansuper@foxmail.com
License: MIT
Platform: UNKNOWN
Classifier: Programming Language :: Python :: 3.7
Classifier: License :: OSI Approved :: MIT License
Classifier: Operating System :: OS Independent
Requires-Dist: msgpack
Requires-Dist: websockets
